setup.py
aliyun_python_sdk.egg-info/PKG-INFO
aliyun_python_sdk.egg-info/SOURCES.txt
aliyun_python_sdk.egg-info/dependency_links.txt
aliyun_python_sdk.egg-info/top_level.txt
api/__init__.py
api/base.py
api/rest/__init__.py