Metadata-Version: 1.0
Name: aliyun-python-sdk
Version: 1.0.0
Summary: All modules of Aliyun python sdk
Home-page: UNKNOWN
Author: Septimus
Author-email: yudan.lyd@alibaba-inc.com
License: License
Keywords: aliyun,sdk,openapi
Platform: any
